histogram/__init__.py
histogram/_pandas.py
histogram_py-0.1.2.dist-info/WHEEL
histogram_py-0.1.2.dist-info/METADATA
histogram_py-0.1.2.dist-info/RECORD
